functions/__init__.py
functions/functions.py
functions_kmazen-0.1.0.dist-info/METADATA
functions_kmazen-0.1.0.dist-info/WHEEL
functions_kmazen-0.1.0.dist-info/RECORD
