Metadata-Version: 2.1
Name: functions-kmazen
Version: 0.1.0
Summary: 
Author: Karolis
Author-email: karolis.mazenis@gmail.com
Requires-Python: >=3.10,<4.0
Classifier: Programming Language :: Python :: 3
Classifier: Programming Language :: Python :: 3.10
Classifier: Programming Language :: Python :: 3.11
Requires-Dist: numpy (>=1.24.3,<2.0.0)
